{
  "birds": [
    {
      "id": "1",
      "name": "Barn Owl",
      "image": "https://arnabrcar24.github.io/birdswb/assets/images/nocturnal-birds/barn-owl.jpg",
      "size": "36",
      "season": "All",
      "gender": "",
      "category": "Nocturnal Birds"
    },
    {
      "id": "2",
      "name": "Brown Fish Owl",
      "image": "https://arnabrcar24.github.io/birdswb/assets/images/nocturnal-birds/brown-fish-owl.jpg",
      "size": "56",
      "season": "All",
      "gender": "",
      "category": "Nocturnal Birds"
    },
    {
      "id": "3",
      "name": "Indian Nightjar",
      "image": "https://arnabrcar24.github.io/birdswb/assets/images/nocturnal-birds/indian-nightjar.jpg",
      "size": "24",
      "season": "All",
      "gender": "",
      "category": "Nocturnal Birds"
    },
    {
      "id": "4",
      "name": "Spotted Owlet",
      "image": "https://arnabrcar24.github.io/birdswb/assets/images/nocturnal-birds/spotted-owlet.jpg",
      "size": "21",
      "season": "All",
      "gender": "",
      "category": "Nocturnal Birds"
    },
    {
      "id": "5",
      "name": "Brahminy Kite",
      "image": "https://arnabrcar24.github.io/birdswb/assets/images/birds-of-prey/brahminy-kite.jpg",
      "size": "48",
      "season": "All",
      "gender": "",
      "category": "Birds of Prey"
    },
    {
      "id": "6",
      "name": "Black Baza",
      "image": "https://arnabrcar24.github.io/birdswb/assets/images/birds-of-prey/black-baza.jpg",
      "size": "33",
      "season": "Winter",
      "gender": "",
      "category": "Birds of Prey"
    },
    {
      "id": "7",
      "name": "Pied Harrier",
      "image": "https://arnabrcar24.github.io/birdswb/assets/images/birds-of-prey/pied-harrier-male.jpg",
      "size": "44",
      "season": "Winter",
      "gender": "Male",
      "category": "Birds of Prey"
    },
    {
      "id": "8",
      "name": "Pied Harrier",
      "image": "https://arnabrcar24.github.io/birdswb/assets/images/birds-of-prey/pied-harrier-female.jpg",
      "size": "44",
      "season": "Winter",
      "gender": "Female",
      "category": "Birds of Prey"
    },
    {
      "id": "9",
      "name": "Ashy Woodswallow",
      "image": "https://arnabrcar24.github.io/birdswb/assets/images/aerial-feeding-birds/ashy-woodswallow.jpg",
      "size": "19",
      "season": "All",
      "gender": "",
      "category": "Aerial Feeding Birds"
    },
    {
      "id": "10",
      "name": "Little Swift",
      "image": "https://arnabrcar24.github.io/birdswb/assets/images/aerial-feeding-birds/little-swift.jpg",
      "size": "12",
      "season": "All",
      "gender": "",
      "category": "Aerial Feeding Birds"
    },
    {
      "id": "11",
      "name": "Wire-tailed Swallow",
      "image": "https://arnabrcar24.github.io/birdswb/assets/images/aerial-feeding-birds/wire-tailed-swallow.jpg",
      "size": "18",
      "season": "All",
      "gender": "",
      "category": "Aerial Feeding Birds"
    },
    {
      "id": "12",
      "name": "Barn Swallow",
      "image": "https://arnabrcar24.github.io/birdswb/assets/images/aerial-feeding-birds/barn-swallow.jpg",
      "size": "18",
      "season": "Winter",
      "gender": "",
      "category": "Aerial Feeding Birds"
    },
    {
      "id": "13",
      "name": "Eurasian Hoopoe",
      "image": "https://arnabrcar24.github.io/birdswb/assets/images/ground-feeding-birds/eurasian-hoopoe.jpg",
      "size": "31",
      "season": "Winter",
      "gender": "",
      "category": "Ground Feeding Birds"
    },
    {
      "id": "14",
      "name": "Indian Peafowl",
      "image": "https://arnabrcar24.github.io/birdswb/assets/images/ground-feeding-birds/indian-peafowl-male.jpg",
      "size": "110",
      "season": "All",
      "gender": "Male",
      "category": "Ground Feeding Birds"
    },
    {
      "id": "15",
      "name": "Indian Peafowl",
      "image": "https://arnabrcar24.github.io/birdswb/assets/images/ground-feeding-birds/indian-peafowl-female.jpg",
      "size": "85",
      "season": "All",
      "gender": "Female",
      "category": "Ground Feeding Birds"
    },
    {
      "id": "16",
      "name": "Indian Pitta",
      "image": "https://arnabrcar24.github.io/birdswb/assets/images/ground-feeding-birds/indian-pitta.jpg",
      "size": "18",
      "season": "Summer",
      "gender": "",
      "category": "Ground Feeding Birds"
    }
  ]
}